speedtest_influx_logger/__init__.py
speedtest_influx_logger/__main__.py
speedtest_influx_logger/main.py
speedtest_influx_logger-0.0.7.dist-info/METADATA
speedtest_influx_logger-0.0.7.dist-info/WHEEL
speedtest_influx_logger-0.0.7.dist-info/entry_points.txt
speedtest_influx_logger-0.0.7.dist-info/top_level.txt
speedtest_influx_logger-0.0.7.dist-info/RECORD
