Metadata-Version: 2.1
Name: speedtest-influx-logger
Version: 0.0.7
Summary: UNKNOWN
Home-page: https://github.com/danstreeter/speedtest-logger
Author: Dan Streeter
Author-email: dan@danstreeter.co.uk
License: License :: OSI Approved :: MIT License
Platform: UNKNOWN
Classifier: Programming Language :: Python
Requires-Python: >=3.8
Requires-Dist: requests (==2.23.0)
Requires-Dist: schedule (==0.6.0)
Requires-Dist: speedtest-cli (==2.1.3)
